smartfunc/__init__.py
smartfunc-1.0.0.dist-info/METADATA
smartfunc-1.0.0.dist-info/WHEEL
smartfunc-1.0.0.dist-info/licenses/LICENSE
smartfunc-1.0.0.dist-info/RECORD
