Metadata-Version: 2.4
Name: smartfunc
Version: 1.0.0
Summary: Turn functions into LLM-powered endpoints using OpenAI SDK
License-File: LICENSE
Requires-Dist: openai>=1.0.0
Requires-Dist: pydantic>=2.0.0
Provides-Extra: test
Requires-Dist: pytest-asyncio>=0.21.0; extra == 'test'
Requires-Dist: pytest-mock>=3.12.0; extra == 'test'
Requires-Dist: pytest>=7.0.0; extra == 'test'
